setup.py
Flask_RedisSession.egg-info/PKG-INFO
Flask_RedisSession.egg-info/SOURCES.txt
Flask_RedisSession.egg-info/dependency_links.txt
Flask_RedisSession.egg-info/not-zip-safe
Flask_RedisSession.egg-info/requires.txt
Flask_RedisSession.egg-info/top_level.txt
flask_redisSession/__init__.py